django_dynamic_shields/__init__.py
django_dynamic_shields/data/ShieldsData.py
django_dynamic_shields/data/__init__.py
django_dynamic_shields/models/DynamicShieldsModel.py
django_dynamic_shields/models/__init__.py
django_dynamic_shields/views/DynamicShieldsView.py
django_dynamic_shields/views/__init__.py
django_dynamic_shields-0.2.8.dist-info/LICENSE
django_dynamic_shields-0.2.8.dist-info/WHEEL
django_dynamic_shields-0.2.8.dist-info/METADATA
django_dynamic_shields-0.2.8.dist-info/RECORD
