Metadata-Version: 2.1
Name: django-dynamic-shields
Version: 0.2.8
Summary: 
Author: Takashi Uno
Author-email: euno.eng@gmail.com
Requires-Python: >=3.7,<4.0
Classifier: Programming Language :: Python :: 3
Classifier: Programming Language :: Python :: 3.7
Classifier: Programming Language :: Python :: 3.8
Classifier: Programming Language :: Python :: 3.9
Classifier: Programming Language :: Python :: 3.10
Requires-Dist: Django (>=3.2,<5.0)
Requires-Dist: typing-extensions (>=4.2.0,<5.0.0)
